pyipng
